README.md
requirements.txt
setup.py
ait_surgeon.egg-info/PKG-INFO
ait_surgeon.egg-info/SOURCES.txt
ait_surgeon.egg-info/dependency_links.txt
ait_surgeon.egg-info/entry_points.txt
ait_surgeon.egg-info/requires.txt
ait_surgeon.egg-info/top_level.txt
auto_optimizer/__init__.py
auto_optimizer/__main__.py
auto_optimizer/ait_main.py
auto_optimizer/model.cfg
auto_optimizer/options.py
auto_optimizer/common/__init__.py
auto_optimizer/common/args_check.py
auto_optimizer/common/click_utils.py
auto_optimizer/common/config.py
auto_optimizer/common/log.py
auto_optimizer/common/register.py
auto_optimizer/common/singleton.py
auto_optimizer/common/utils.py
auto_optimizer/graph_optimizer/__init__.py
auto_optimizer/graph_optimizer/optimizer.py
auto_optimizer/graph_refactor/__init__.py
auto_optimizer/graph_refactor/interface/__init__.py
auto_optimizer/graph_refactor/interface/base_graph.py
auto_optimizer/graph_refactor/interface/base_node.py
auto_optimizer/graph_refactor/onnx/__init__.py
auto_optimizer/graph_refactor/onnx/graph.py
auto_optimizer/graph_refactor/onnx/node.py
auto_optimizer/inference_engine/__init__.py
auto_optimizer/inference_engine/data_process_factory.py
auto_optimizer/inference_engine/calibration/__init__.py
auto_optimizer/inference_engine/common/__init__.py
auto_optimizer/inference_engine/common/utils.py
auto_optimizer/inference_engine/datasets/__init__.py
auto_optimizer/inference_engine/datasets/dataset_base.py
auto_optimizer/inference_engine/datasets/language/__init__.py
auto_optimizer/inference_engine/datasets/speech/__init__.py
auto_optimizer/inference_engine/datasets/vision/__init__.py
auto_optimizer/inference_engine/datasets/vision/imagenet.py
auto_optimizer/inference_engine/evaluate/__init__.py
auto_optimizer/inference_engine/evaluate/evaluate_base.py
auto_optimizer/inference_engine/evaluate/language/__init__.py
auto_optimizer/inference_engine/evaluate/speech/__init__.py
auto_optimizer/inference_engine/inference/__init__.py
auto_optimizer/inference_engine/inference/acl_inference.py
auto_optimizer/inference_engine/inference/inference_base.py
auto_optimizer/inference_engine/inference/onnx_inference.py
auto_optimizer/inference_engine/model_convert/__init__.py
