Metadata-Version: 2.1
Name: ait-surgeon
Version: 0.1.1
Summary: auto optimizer
Home-page: https://gitee.com/ascend/ait
License: Apache-2.0
Keywords: auto optimizer
Classifier: Development Status :: 3 - Alpha
Classifier: Intended Audience :: Developers
Classifier: License :: OSI Approved :: Apache Software License
Classifier: Programming Language :: Python :: 3 :: Only
Classifier: Programming Language :: Python :: 3.7
Classifier: Programming Language :: Python :: 3.8
Classifier: Programming Language :: Python :: 3.9
Classifier: Topic :: Scientific/Engineering
Classifier: Topic :: Software Development
Requires-Python: >=3.7
Requires-Dist: ms-ait~=7.0.0a2
Requires-Dist: onnx>=1.14.0
Requires-Dist: numpy>=1.21.0
Requires-Dist: onnxruntime<1.16.0,>=1.14.1
Requires-Dist: setuptools>=63.2.0
Requires-Dist: click>=8.1.3
Requires-Dist: click_aliases>=1.0.1
Requires-Dist: skl2onnx>=1.14.1
Provides-Extra: simplify
Requires-Dist: onnx-simplifier>=0.3.6; extra == "simplify"
